py_cassandra_journal_forwarder
